STanalysis/__init__.py
STanalysis/point_extraction.py
stanalysis-0.1.4.dist-info/METADATA
stanalysis-0.1.4.dist-info/WHEEL
stanalysis-0.1.4.dist-info/top_level.txt
stanalysis-0.1.4.dist-info/RECORD
