Metadata-Version: 2.4
Name: STanalysis
Version: 0.1.4
Summary: Air pollution data extraction and comparison with different sources - HealthyPlanet Project - AWI
Requires-Python: >=3.12
Requires-Dist: matplotlib>=3.10.3
Requires-Dist: pandas>=2.2.3
Requires-Dist: xarray>=2025.4.0
Requires-Dist: geopandas>=1.1.0
Requires-Dist: scipy>=1.15.3
Requires-Dist: pyproj>=3.6
Requires-Dist: twine>=6.1.0
Requires-Dist: build>=1.2.2.post1
Requires-Dist: bumpver>=2024.1130
Requires-Dist: seaborn>=0.13.2
Requires-Dist: numpy<2.0.0,>=1.26.4
Requires-Dist: netCDF4>=1.6.3
Requires-Dist: requests>=2.32.3
Requires-Dist: pydantic>=2.8.0
Provides-Extra: dev
Requires-Dist: pytest; extra == "dev"
Requires-Dist: ruff; extra == "dev"
Requires-Dist: mypy; extra == "dev"
Requires-Dist: tomli>=2.0.1; extra == "dev"
